airflux/__init__.py
airflux/cli.py
airflux-1.0.0.dist-info/LICENSE
airflux-1.0.0.dist-info/METADATA
airflux-1.0.0.dist-info/WHEEL
airflux-1.0.0.dist-info/entry_points.txt
airflux-1.0.0.dist-info/top_level.txt
airflux-1.0.0.dist-info/RECORD
