Metadata-Version: 2.1
Name: airflux
Version: 1.0.0
Summary: A simple Airflow installer and tmux sesssion manager
Author-email: Ross Turk <ross@rossturk.com>
License: Apache License
Project-URL: Homepage, https://github.com/rossturk/airflux
Keywords: airflow,tmux
Classifier: License :: OSI Approved :: Apache Software License
Classifier: Programming Language :: Python
Classifier: Programming Language :: Python :: 3
Requires-Python: >=3.0
License-File: LICENSE
Requires-Dist: libtmux
Requires-Dist: rich-click
Requires-Dist: GitPython
Requires-Dist: requests
Provides-Extra: dev
Requires-Dist: black ; extra == 'dev'
Requires-Dist: bumpver ; extra == 'dev'
